paperplotlib/__init__.py
paperplotlib/bar_graph.py
paperplotlib/color.css
paperplotlib/color.py
paperplotlib/consola-1.ttf
paperplotlib/graph.py
paperplotlib/line_graph.py
paperplotlib-0.0.7.dist-info/LICENSE
paperplotlib-0.0.7.dist-info/METADATA
paperplotlib-0.0.7.dist-info/WHEEL
paperplotlib-0.0.7.dist-info/RECORD
