Metadata-Version: 2.1
Name: paperplotlib
Version: 0.0.7
Summary: 论文实验数据绘图
Home-page: https://github.com/luzhixing12345/paperplotlib
License: MIT
Author: luzhixing12345
Author-email: luzhixing12345@163.com
Requires-Python: >=3.7,<4.0
Classifier: License :: OSI Approved :: MIT License
Classifier: Programming Language :: Python :: 3
Classifier: Programming Language :: Python :: 3.7
Classifier: Programming Language :: Python :: 3.8
Classifier: Programming Language :: Python :: 3.9
Classifier: Programming Language :: Python :: 3.10
Classifier: Programming Language :: Python :: 3.11
Requires-Dist: matplotlib (>=3.7.0,<4.0.0)
Requires-Dist: numpy (>=1.23.5,<2.0.0)
Project-URL: Documentation, https://luzhixing12345.github.io/paperplotlib/
Project-URL: Repository, https://github.com/luzhixing12345/paperplotlib
